scimilarity/__init__.py
scimilarity/anndata_data_models.py
scimilarity/cell_annotation.py
scimilarity/cell_embedding.py
scimilarity/cell_query.py
scimilarity/cell_search_knn.py
scimilarity/interpreter.py
scimilarity/nn_models.py
scimilarity/ontologies.py
scimilarity/tiledb_data_models.py
scimilarity/training_models.py
scimilarity/triplet_selector.py
scimilarity/utils.py
scimilarity/visualizations.py
scimilarity/zarr_data_models.py
scimilarity/zarr_dataset.py
scimilarity-0.4.1.dist-info/licenses/LICENSE
scimilarity-0.4.1.dist-info/METADATA
scimilarity-0.4.1.dist-info/WHEEL
scimilarity-0.4.1.dist-info/top_level.txt
scimilarity-0.4.1.dist-info/RECORD
